zipnn_core.cpython-312-darwin.so
zipnn/__init__.py
zipnn/util_header.py
zipnn/util_patch.py
zipnn/util_safetensors.py
zipnn/util_torch.py
zipnn/zipnn.py
zipnn-0.5.3.dist-info/LICENSE.txt
zipnn-0.5.3.dist-info/METADATA
zipnn-0.5.3.dist-info/WHEEL
zipnn-0.5.3.dist-info/top_level.txt
zipnn-0.5.3.dist-info/RECORD
