Metadata-Version: 2.1
Name: zipnn
Version: 0.5.3
Summary: A Lossless Compression Library for AI pipelines
Home-page: https://github.com/zipnn/zipnn
Author: ZipNN Contributors
Classifier: Programming Language :: Python :: 3
Classifier: License :: OSI Approved :: MIT License
Classifier: Operating System :: OS Independent
Requires-Python: >=3.6
License-File: LICENSE.txt
Requires-Dist: numpy>=1.17.0
Requires-Dist: safetensors>=0.4.0
Requires-Dist: torch>=2.0.0
